outlier/__init__.py
outlier/__main__.py
outlier/client.py
outlier/server.py
outlier/biz/__init__.py
outlier/biz/beans.py
outlier/biz/bizservice.py
outlier/encryption/__init__.py
outlier/encryption/protocol.py
outlier/encryption/sessionservice.py
outlier/tools/__init__.py
outlier/tools/chatterminal.py
outlier/tools/decorators.py
outlier/tools/events.py
outlier/tools/threadpool.py
outlier/tools/utils.py
outlier/transmission/__init__.py
outlier/transmission/tcpservice.py
outlierchat-0.0.25.dist-info/LICENSE
outlierchat-0.0.25.dist-info/METADATA
outlierchat-0.0.25.dist-info/WHEEL
outlierchat-0.0.25.dist-info/top_level.txt
outlierchat-0.0.25.dist-info/RECORD
