Metadata-Version: 2.1
Name: outlierchat
Version: 0.0.25
Summary: A simple server to build a secret channel for chat.
Home-page: 
Author: Thetis
Author-email: 736396627@qq.com
Classifier: Programming Language :: Python :: 3
Classifier: License :: OSI Approved :: Apache Software License
Classifier: Operating System :: OS Independent
Requires-Python: >3.6
License-File: LICENSE
Requires-Dist: rsa (>=4.9)
Requires-Dist: pyDes (>=2.0.1)
